timelink/__init__.py
timelink/alembic.ini
timelink/cli.py
timelink/timelink.py
timelink/api/__init__.py
timelink/api/crud.py
timelink/api/database.py
timelink/api/database_kleio.py
timelink/api/database_metadata.py
timelink/api/database_postgres.py
timelink/api/database_query.py
timelink/api/database_sqlite.py
timelink/api/database_utils.py
timelink/api/database_views.py
timelink/api/schemas.py
timelink/api/views.py
timelink/api/models/__init__.py
timelink/api/models/act.py
timelink/api/models/aregister.py
timelink/api/models/attribute.py
timelink/api/models/base.py
timelink/api/models/base_class.py
timelink/api/models/base_mappings.py
timelink/api/models/entity.py
timelink/api/models/geoentity.py
timelink/api/models/object.py
timelink/api/models/person.py
timelink/api/models/pom_som_mapper.py
timelink/api/models/relation.py
timelink/api/models/rentity.py
timelink/api/models/source.py
timelink/api/models/system.py
timelink/app/__init__.py
timelink/app/dependencies.py
timelink/app/main.py
timelink/app/backend/__init__.py
timelink/app/backend/settings.py
timelink/app/backend/timelink_webapp.py
timelink/app/models/__init__.py
timelink/app/models/project.py
timelink/app/models/user.py
timelink/app/models/user_database.py
timelink/app/schemas/__init__.py
timelink/app/schemas/project.py
timelink/app/schemas/user.py
timelink/app/services/__init__.py
timelink/app/services/auth.py
timelink/app/services/syslog.py
timelink/app/services/syspar.py
timelink/app/static/__init__.py
timelink/app/static/hello.html
timelink/app/templates/entity_attr_rel.md
timelink/app/templates/index.html
timelink/app/templates/item.html
timelink/app/templates/tables.html
timelink/app/templates/te-quick-start.html
timelink/app/templates/markdown/base/README.md
timelink/app/templates/markdown/base/entity_attr_rel.j2
timelink/app/templates/markdown/base/entity_attr_rel.md
timelink/app/templates/markdown/base/entity_contains.j2
timelink/app/templates/markdown/base/entity_default_markdown.j2
timelink-1.1.31.dist-info/licenses/AUTHORS.rst
timelink-1.1.31.dist-info/licenses/LICENSE
timelink-1.1.31.dist-info/METADATA
timelink-1.1.31.dist-info/WHEEL
timelink-1.1.31.dist-info/entry_points.txt
timelink-1.1.31.dist-info/top_level.txt
timelink-1.1.31.dist-info/RECORD
