Metadata-Version: 2.4
Name: timelink
Version: 1.1.31
Summary: Timelink is an information system for person related information collected from historical sources.
Home-page: https://github.com/time-link/timelink-py
Author: Joaquim Ramos de Carvalho
Author-email: Joaquim Ramos de Carvalho <joaquimcarvalho@mpu.edu.mo>
License: MIT
Project-URL: Documentation, https://timelink-py.readthedocs.io/
Project-URL: Source Code, https://github.com/time-link/timelink-py
Project-URL: Bug Tracker, https://github.com/time-link/timelink-py/issues
Project-URL: Homepage, https://github.com/time-link/timelink-py
Keywords: timelink,history,prosopography,kleio,historical-data
Classifier: Development Status :: 3 - Alpha
Classifier: Intended Audience :: Developers
Classifier: Intended Audience :: Science/Research
Classifier: License :: OSI Approved :: MIT License
Classifier: Natural Language :: English
Classifier: Programming Language :: Python :: 3
Classifier: Programming Language :: Python :: 3.10
Classifier: Programming Language :: Python :: 3.11
Classifier: Programming Language :: Python :: 3.12
Classifier: Programming Language :: Python :: 3.13
Classifier: Topic :: Software Development :: Libraries :: Python Modules
Classifier: Topic :: Sociology :: History
Requires-Python: >=3.10
License-File: LICENSE
License-File: AUTHORS.rst
Requires-Dist: typer>=0.9.0
Requires-Dist: fastapi
Requires-Dist: matplotlib
Requires-Dist: sqlalchemy
Requires-Dist: sqlalchemy-utils
Requires-Dist: alembic
Requires-Dist: pydantic
Requires-Dist: pydantic-settings
Requires-Dist: python-dotenv
Requires-Dist: python-box
Requires-Dist: python-multipart
Requires-Dist: psycopg2-binary
Requires-Dist: py-markdown-table
Requires-Dist: python-jose[cryptography]
Requires-Dist: pandas
Requires-Dist: docker
Requires-Dist: jsonrpcclient
Requires-Dist: ipython
Requires-Dist: uvicorn
Requires-Dist: requests
Provides-Extra: dev
Requires-Dist: alabaster==0.7.12; extra == "dev"
Requires-Dist: argh~=0.28.1; extra == "dev"
Requires-Dist: black>=24.3.0; extra == "dev"
Requires-Dist: build; extra == "dev"
Requires-Dist: bump2version==1.0.1; extra == "dev"
Requires-Dist: coverage==5.5; extra == "dev"
Requires-Dist: docutils>=0.19.0; extra == "dev"
Requires-Dist: flake8-bugbear==24.4.26; extra == "dev"
Requires-Dist: flake8==7.1.1; extra == "dev"
Requires-Dist: nbsphinx; extra == "dev"
Requires-Dist: nbval>=0.10.0; extra == "dev"
Requires-Dist: pipdeptree; extra == "dev"
Requires-Dist: pytest>=8; extra == "dev"
Requires-Dist: pytest-profiling; extra == "dev"
Requires-Dist: snakeviz; extra == "dev"
Requires-Dist: sphinx_rtd_theme>=1.2.0; extra == "dev"
Requires-Dist: tox; extra == "dev"
Requires-Dist: twine==4.0.2; extra == "dev"
Requires-Dist: watchdog==2.1.3; extra == "dev"
Provides-Extra: test
Requires-Dist: pytest>=8; extra == "test"
Requires-Dist: coverage==5.5; extra == "test"
Requires-Dist: nbval>=0.10.0; extra == "test"
Dynamic: author
Dynamic: home-page
Dynamic: license-file
Dynamic: requires-python
